zigpy_znp/__init__.py
zigpy_znp/api.py
zigpy_znp/config.py
zigpy_znp/const.py
zigpy_znp/exceptions.py
zigpy_znp/frames.py
zigpy_znp/logger.py
zigpy_znp/nvram.py
zigpy_znp/uart.py
zigpy_znp/utils.py
zigpy_znp/commands/__init__.py
zigpy_znp/commands/af.py
zigpy_znp/commands/app.py
zigpy_znp/commands/app_config.py
zigpy_znp/commands/mac.py
zigpy_znp/commands/rpc_error.py
zigpy_znp/commands/sapi.py
zigpy_znp/commands/sys.py
zigpy_znp/commands/ubl.py
zigpy_znp/commands/util.py
zigpy_znp/commands/zdo.py
zigpy_znp/commands/zgp.py
zigpy_znp/commands/znp.py
zigpy_znp/tools/__init__.py
zigpy_znp/tools/common.py
zigpy_znp/tools/energy_scan.py
zigpy_znp/tools/flash_read.py
zigpy_znp/tools/flash_write.py
zigpy_znp/tools/network_backup.py
zigpy_znp/tools/network_restore.py
zigpy_znp/tools/network_scan.py
zigpy_znp/tools/nvram_read.py
zigpy_znp/tools/nvram_reset.py
zigpy_znp/tools/nvram_write.py
zigpy_znp/types/__init__.py
zigpy_znp/types/basic.py
zigpy_znp/types/commands.py
zigpy_znp/types/cstruct.py
zigpy_znp/types/named.py
zigpy_znp/types/nvids.py
zigpy_znp/types/structs.py
zigpy_znp/types/zigpy_types.py
zigpy_znp/zigbee/__init__.py
zigpy_znp/zigbee/application.py
zigpy_znp/zigbee/device.py
zigpy_znp/znp/__init__.py
zigpy_znp/znp/security.py
zigpy_znp-0.14.3.dist-info/licenses/COPYING
zigpy_znp-0.14.3.dist-info/licenses/LICENSE
zigpy_znp-0.14.3.dist-info/METADATA
zigpy_znp-0.14.3.dist-info/WHEEL
zigpy_znp-0.14.3.dist-info/top_level.txt
zigpy_znp-0.14.3.dist-info/RECORD
