Metadata-Version: 2.4
Name: zigpy-znp
Version: 0.14.3
Summary: A library for zigpy which communicates with TI ZNP radios
Author-email: Alexei Chetroi <alexei.chetroi@outlook.com>
License: GPL-3.0
Project-URL: repository, https://github.com/zigpy/zigpy-znp
Requires-Python: >=3.8
License-File: LICENSE
License-File: COPYING
Requires-Dist: zigpy>=0.91.2
Requires-Dist: async-timeout; python_version < "3.11"
Requires-Dist: voluptuous
Requires-Dist: coloredlogs
Requires-Dist: jsonschema
Provides-Extra: testing
Requires-Dist: pytest>=7.3.1; extra == "testing"
Requires-Dist: pytest-asyncio>=0.21.0; extra == "testing"
Requires-Dist: pytest-timeout>=2.1.0; extra == "testing"
Requires-Dist: pytest-mock>=3.10.0; extra == "testing"
Requires-Dist: pytest-cov>=4.1.0; extra == "testing"
Dynamic: license-file
